Metadata-Version: 2.1
Name: livecellx
Version: 0.0.2
Summary: live-cell analysis package including instance segmentation and tracker
Author-email: Ke Ni <ken67@pitt.edu>
Requires-Python: >=3.7
Classifier: License :: OSI Approved :: GNU General Public License v3 (GPLv3)
Project-URL: documentation, https://github.com/xing-lab-pitt/LiveCellTracker-dev
Project-URL: homepage, https://github.com/xing-lab-pitt/LiveCellTracker-dev
Project-URL: repository, https://github.com/xing-lab-pitt/LiveCellTracker-dev
